symmetry_representation/__init__.py
symmetry_representation/_cli.py
symmetry_representation/_compatibility.py
symmetry_representation/_legacy_io.py
symmetry_representation/_sym_op.py
symmetry_representation/_version.py
symmetry_representation/io.py
symmetry_representation-0.1.0.dist-info/DESCRIPTION.rst
symmetry_representation-0.1.0.dist-info/METADATA
symmetry_representation-0.1.0.dist-info/RECORD
symmetry_representation-0.1.0.dist-info/WHEEL
symmetry_representation-0.1.0.dist-info/entry_points.txt
symmetry_representation-0.1.0.dist-info/metadata.json
symmetry_representation-0.1.0.dist-info/top_level.txt
