Metadata-Version: 2.0
Name: symmetry-representation
Version: 0.1.0
Summary: Provides an interface to describe symmetry representations.
Home-page: http://z2pack.ethz.ch/symmetry-representation
Author: Dominik Gresch
Author-email: greschd@gmx.ch
License: GPL
Platform: UNKNOWN
Classifier: License :: OSI Approved :: GNU General Public License v3 (GPLv3)
Classifier: Natural Language :: English
Classifier: Operating System :: Unix
Classifier: Programming Language :: Python :: 3
Classifier: Programming Language :: Python :: 3.4
Classifier: Programming Language :: Python :: 3.5
Classifier: Programming Language :: Python :: 3.6
Classifier: Intended Audience :: Science/Research
Classifier: Topic :: Scientific/Engineering :: Physics
Classifier: Development Status :: 4 - Beta
Requires-Dist: numpy
Requires-Dist: fsc.export
Requires-Dist: fsc.hdf5-io
Requires-Dist: h5py
Requires-Dist: pymatgen
Requires-Dist: click
Provides-Extra: dev
Requires-Dist: pytest; extra == 'dev'
Requires-Dist: pytest-cov; extra == 'dev'
Requires-Dist: yapf; extra == 'dev'
Requires-Dist: pre-commit; extra == 'dev'
Requires-Dist: sphinx; extra == 'dev'
Requires-Dist: sphinx-rtd-theme; extra == 'dev'
